setup.cfg
setup.py
tpilib/__init__.py
tpilib/async_.py
tpilib/sync_.py
tpilib.egg-info/PKG-INFO
tpilib.egg-info/SOURCES.txt
tpilib.egg-info/dependency_links.txt
tpilib.egg-info/top_level.txt