Metadata-Version: 2.1
Name: tpilib
Version: 0.1.2.5-7
Summary: Python module for edu-tpi.donstu
Home-page: https://github.com/febdaynik/tpilib
Author: Feb
Author-email: drons_dron@mail.ru
